{"__type__":"cc.SpriteAtlas","_name":"bigbabol-icon.plist","_spriteFrames":{"WIND":{"__uuid__":"57BfwvVeZATIwNrHJZhvQ/"},"anim001":{"__uuid__":"1aECvpDnpAhbgQwk9FlVyX"},"anim002":{"__uuid__":"7faIwhV3FPkaCSsn+s2MHV"},"anim004":{"__uuid__":"feDY2n1YdBwoAOachZ8OeH"},"anim005":{"__uuid__":"62hc8qnEVONYoPhs4v/TN0"},"ef01":{"__uuid__":"60z9DQ7DpI/qn7wnAekkH+"},"ef02":{"__uuid__":"1dFJ1yo5NGXLjvETCFRDO3"},"ef03":{"__uuid__":"68z8D8hX1ITbKS7bNTPczR"},"ef04":{"__uuid__":"c0xhPTjV5HDKvZXpty4WzQ"},"ef05":{"__uuid__":"b2RaYA8rxOLK6HVXzbQ4AI"},"ef06":{"__uuid__":"9cXgf7ePdOtpRnJ91A/POM"},"ef07":{"__uuid__":"a3B/anUoROhpId892MBYrl"},"ef08":{"__uuid__":"e0kMacERRFcqwDwPD4cLCj"},"ef09":{"__uuid__":"80EIDdyvtJtoNbMrjkYdCC"},"icon001":{"__uuid__":"02TaRxusZMMoEY1kAd+yRO"},"icon002":{"__uuid__":"50xpAcWWFOrZcHumh2ecPn"},"icon003":{"__uuid__":"676TJnGzFKF7MhqGjR1MLJ"},"icon004":{"__uuid__":"cbRg5F+wRGaLVoNdYkOxmH"},"icon005":{"__uuid__":"1d7GGLhyBD/LMP0xBNvX5+"},"icon006":{"__uuid__":"cdxrsmryBNA6dj/mGbF1MI"},"icon007":{"__uuid__":"d81MW/bnhFJIbL0tO4VDmI"}}}