{"__type__":"cc.SpriteAtlas","_name":"MegaJackpot.plist","_spriteFrames":{"megajackpot_betting_1":{"__uuid__":"c4OXvZgvNM7KG+1ouNEYk/"},"megajackpot_betting_1_off":{"__uuid__":"47snFNlvlIuoYo6tAA9s49"},"megajackpot_betting_2":{"__uuid__":"b0jeBkxoxEzrjBlzjskGnb"},"megajackpot_betting_2_off":{"__uuid__":"c9nmzvmQdF2bVjy2Adf5DB"},"megajackpot_betting_3":{"__uuid__":"eev9A9fYVMSabIW54c6Bfc"},"megajackpot_betting_3_off":{"__uuid__":"4aYKym9GxC+Jq6wHboJcFQ"},"megajackpot_bg_0":{"__uuid__":"8aCO6T8ItOpoIkpqVvBxJ1"},"megajackpot_close_bt":{"__uuid__":"5eDTlAH5JHgZ8qcUH5bttg"},"megajackpot_history_bt":{"__uuid__":"40PIgwK5pPwL5MSjdursOd"},"megajackpot_info_bt":{"__uuid__":"e9bpWhxXNMBpNO7PwdHbbe"},"megajackpot_rank_bt":{"__uuid__":"c5aNAcijRGWaSNt6Zb56Yy"},"megajackpot_spin":{"__uuid__":"021m7TfERNOJfWENCQnC0m"},"megajackpot_spin_1":{"__uuid__":"55ISKUTjtIEY4aXmYFJT9+"},"megajackpot_spin_2":{"__uuid__":"db5i8Tjo1NZbIq15KONth9"},"megajackpot_spin_3":{"__uuid__":"af7FhMFFNJi7h2LHvHH0SJ"},"megajackpot_spin_bt":{"__uuid__":"07R77zNepExJCUFcagb0Zv"},"megajackpot_spin_bt_off":{"__uuid__":"5aPAI6y1pMOrwjiqpL99Ff"},"megajackpot_win_highlight":{"__uuid__":"19e9/kqeBEKokzz/s6T9pF"}}}