{"__type__":"cc.SpriteAtlas","_name":"mini-game-button.plist","_spriteFrames":{"button-chat":{"__uuid__":"d8jVcTx/BDRaESpljePftw"},"button-close-2":{"__uuid__":"b2mqjCrchEfJOYP+1Us2Uy"},"button-close":{"__uuid__":"bdUJfvD4VDkosqDGDpnWS3"},"button-down":{"__uuid__":"7fZyjHSaJJD5PtO9rwC5tc"},"button-help":{"__uuid__":"9esKhHFQ5Ln70qaTN6DVwQ"},"button-next-preview-2":{"__uuid__":"dc3qYL7M5Po6LIPcM6jpyH"},"button-next-preview":{"__uuid__":"08e1K+9DZIhIRr1+ubm1Z7"},"button-rank":{"__uuid__":"21GAabUQRDIq7AHeSkOztG"},"button-send":{"__uuid__":"b78YgD25ZLhrEQVawf57hL"},"button-tutorial":{"__uuid__":"29KIum8rVNRIFsNUgqj4Cr"},"icon-chip-bg":{"__uuid__":"13OmTxO4dOtqL1ryEZlpR6"}}}